eris
lokey
