Metadata-Version: 1.1
Name: lokey
Version: 0.5.0
Summary: A tool to convert between different cryptographic key formats
Home-page: https://github.com/jpf/lokey
Author: Joel Franusic
Author-email: jfranusic@gmail.com
License: UNKNOWN
Download-URL: https://github.com/jpf/lokey/archive/0.5.0.tar.gz
Keywords: rsa,ssh,pgp,x509,jwk
Platform: UNKNOWN
